{"images/Mobile%20testing-bro.svg":["images/Mobile%20testing-bro.svg"],"images/Online%20test-bro.svg":["images/Online%20test-bro.svg"],"images/Processing-cuate.svg":["images/Processing-cuate.svg"],"images/Robot%20face-bro.svg":["images/Robot%20face-bro.svg"],"images/Software%20engineer-rafiki.svg":["images/Software%20engineer-rafiki.svg"],"images/Task-amico.svg":["images/Task-amico.svg"],"images/Task-pana.svg":["images/Task-pana.svg"],"images/bgs.png":["images/bgs.png"],"images/crossplatform.svg":["images/crossplatform.svg"],"images/robot.json":["images/robot.json"],"packages/cupertino_icons/assets/CupertinoIcons.ttf":["packages/cupertino_icons/assets/CupertinoIcons.ttf"]}